{
  "collection": {
    "_": {
      "postman_id": "56d79a10-7374-4e37-b2bb-f2d710fa749c",
      "exporter_id": "28319607"
    },
    "item": [
      {
        "id": "699a3900-3faf-421c-b4d4-af805d6ff6e6",
        "name": "1.POST_CreateUser",
        "request": {
          "url": {
            "path": [
              "public",
              "v2",
              "users"
            ],
            "host": [
              "{{WorkFlowBaseURL}}"
            ],
            "query": [],
            "variable": []
          },
          "header": [
            {
              "key": "Authorization",
              "value": "{{WorkFlowTokenID}}"
            }
          ],
          "method": "POST",
          "body": {
            "mode": "raw",
            "raw": "{\r\n    \"name\": \"{{$randomFirstName}}\",//this is name \r\n    \"email\": \"sha_{{$randomEmail}}\",// this is email id\r\n    \"gender\": \"male\", // this gender identity\r\n    \"status\": \"inactive\" // user status\r\n}",
            "options": {
              "raw": {
                "language": "json"
              }
            }
          }
        },
        "response": [],
        "event": [
          {
            "listen": "test",
            "script": {
              "id": "c709845b-1a12-449f-be8c-6ef20427a30d",
              "type": "text/javascript",
              "packages": {},
              "exec": [
                "const res = pm.response.json();\r",
                "const userId = res.id;\r",
                "const userName = res.name;\r",
                "const userEmail = res.email;\r",
                "const userGender = res.gender;\r",
                "const userStatus = res.status;\r",
                "\r",
                "console.log(\"User Id is :\"+userId);\r",
                "console.log(\"User NAme is :\"+userName);\r",
                "console.log(\"User MailID is :\"+userEmail);\r",
                "console.log(\"User Gender is :\"+userGender);\r",
                "console.log(\"User Gender is :\"+userStatus);\r",
                "\r",
                "//use local variable to set the userid\r",
                "pm.variables.set(\"user_id\",userId);\r",
                "\r",
                "pm.test(\"Status code is 201\", function () {\r",
                "    pm.response.to.have.status(201);\r",
                "});\r",
                "\r",
                "\r",
                ""
              ],
              "_lastExecutionId": "138e2c59-44a4-4551-9d81-fb623489efad"
            }
          }
        ]
      },
      {
        "id": "b2e41b24-5776-4ce3-94ad-11185a76c607",
        "name": "2.GET_CreatedUser",
        "request": {
          "url": {
            "path": [
              "public",
              "v2",
              "users",
              "{{user_id}}"
            ],
            "host": [
              "{{WorkFlowBaseURL}}"
            ],
            "query": [],
            "variable": []
          },
          "header": [
            {
              "key": "Authorization",
              "value": "Bearer 8cc2fb2d65333fab4f7a3aa752662dac66d862fb2afa9a5578155b94a3e9d32f"
            }
          ],
          "method": "GET",
          "body": {
            "mode": "raw",
            "raw": "{\r\n    \"name\": \"{{$randomFirstName}}\",\r\n    \"email\": \"sha_{{$randomEmail}}\",\r\n    \"gender\": \"male\",\r\n    \"status\": \"inactive\"\r\n}",
            "options": {
              "raw": {
                "language": "json"
              }
            }
          }
        },
        "response": [],
        "event": [
          {
            "listen": "test",
            "script": {
              "id": "aaa8f7e5-1603-4765-b9fa-d5bac7281d37",
              "type": "text/javascript",
              "packages": {},
              "exec": [
                "pm.test(\"Status code is 200\", function () {\r",
                "    pm.response.to.have.status(200);\r",
                "});\r",
                ""
              ],
              "_lastExecutionId": "13cc12bd-2d7d-4df2-860c-16aae55c61c1"
            }
          }
        ],
        "protocolProfileBehavior": {
          "disableBodyPruning": true
        }
      },
      {
        "id": "96381c77-108a-4dc3-ae6b-3bd85708c723",
        "name": "3.PATCH_UpdateUSer",
        "request": {
          "url": {
            "path": [
              "public",
              "v2",
              "users",
              "",
              "{{user_id}}"
            ],
            "host": [
              "{{WorkFlowBaseURL}}"
            ],
            "query": [],
            "variable": []
          },
          "header": [
            {
              "key": "Authorization",
              "value": "{{WorkFlowTokenID}}"
            }
          ],
          "method": "PATCH",
          "body": {
            "mode": "raw",
            "raw": "{\r\n    \"name\": \"{{$randomFirstName}}\",//this is name \r\n    \"email\": \"sha_{{$randomEmail}}\"// this is email id\r\n  \r\n}",
            "options": {
              "raw": {
                "language": "json"
              }
            }
          }
        },
        "response": [],
        "event": [
          {
            "listen": "test",
            "script": {
              "id": "d0d73b52-3a5e-451d-b7ee-07463a452ddf",
              "type": "text/javascript",
              "packages": {},
              "exec": [
                "pm.test(\"Status code is 200\", function () {\r",
                "    pm.response.to.have.status(200);\r",
                "});\r",
                ""
              ],
              "_lastExecutionId": "d8fddab8-0446-4a44-ba77-5c35e8d9c807"
            }
          }
        ]
      },
      {
        "id": "2a0c0a6d-a6a8-4943-8c7f-fda0a2fd2332",
        "name": "4.DELETE-User",
        "request": {
          "url": {
            "path": [
              "public",
              "v2",
              "users",
              "{{user_id}}"
            ],
            "host": [
              "{{WorkFlowBaseURL}}"
            ],
            "query": [],
            "variable": []
          },
          "header": [
            {
              "key": "Authorization",
              "value": "Bearer 8cc2fb2d65333fab4f7a3aa752662dac66d862fb2afa9a5578155b94a3e9d32f"
            }
          ],
          "method": "DELETE",
          "body": {
            "mode": "raw",
            "raw": "",
            "options": {
              "raw": {
                "language": "json"
              }
            }
          }
        },
        "response": [],
        "event": [
          {
            "listen": "test",
            "script": {
              "id": "60c239ca-97ac-4953-849a-562af59ec5fc",
              "type": "text/javascript",
              "packages": {},
              "exec": [
                "pm.test(\"Status code is 204\", function () {\r",
                "    pm.response.to.have.status(204);\r",
                "});\r",
                ""
              ],
              "_lastExecutionId": "e4d78ded-e4b0-4e22-bd6e-b1c4c9498a2d"
            }
          }
        ]
      },
      {
        "id": "0aef6883-42a9-4bf2-b49f-54f661b2d1fd",
        "name": "5.GET_DEletedUser",
        "request": {
          "url": {
            "path": [
              "public",
              "v2",
              "users",
              "{{user_id}}"
            ],
            "host": [
              "{{WorkFlowBaseURL}}"
            ],
            "query": [],
            "variable": []
          },
          "header": [
            {
              "key": "Authorization",
              "value": "Bearer 8cc2fb2d65333fab4f7a3aa752662dac66d862fb2afa9a5578155b94a3e9d32f"
            }
          ],
          "method": "GET",
          "body": {
            "mode": "raw",
            "raw": "{\r\n    \"name\": \"{{$randomFirstName}}\",\r\n    \"email\": \"sha_{{$randomEmail}}\",\r\n    \"gender\": \"male\",\r\n    \"status\": \"inactive\"\r\n}",
            "options": {
              "raw": {
                "language": "json"
              }
            }
          }
        },
        "response": [],
        "event": [
          {
            "listen": "test",
            "script": {
              "id": "b1277eaf-d3c7-497f-860e-93abf27911c2",
              "type": "text/javascript",
              "packages": {},
              "exec": [
                "pm.test(\"Status code is 404\", function () {\r",
                "    pm.response.to.have.status(404);\r",
                "});\r",
                ""
              ],
              "_lastExecutionId": "6e6b8c2e-0e6c-4432-8afc-12b4dbcb10ee"
            }
          }
        ],
        "protocolProfileBehavior": {
          "disableBodyPruning": true
        }
      }
    ],
    "event": [
      {
        "listen": "prerequest",
        "script": {
          "id": "6ab75bfa-c8d1-4432-87d3-a3811ba46d9b",
          "type": "text/javascript",
          "packages": {},
          "exec": [
            ""
          ],
          "_lastExecutionId": "a212b021-1cf5-49e1-965b-7c0e0ecde0cd"
        }
      },
      {
        "listen": "test",
        "script": {
          "id": "011bac46-afb7-4483-a1dd-1a0d3dc69ef7",
          "type": "text/javascript",
          "packages": {},
          "exec": [
            "pm.test(\"Response time is less than 5000ms\", function () {\r",
            "    pm.expect(pm.response.responseTime).to.be.below(5000);\r",
            "});"
          ],
          "_lastExecutionId": "6f71f7c5-a1fc-4100-8671-807600f68759"
        }
      }
    ],
    "variable": [],
    "info": {
      "_postman_id": "56d79a10-7374-4e37-b2bb-f2d710fa749c",
      "name": "WorkFlow_Test",
      "schema": "https://schema.getpostman.com/json/collection/v2.1.0/collection.json"
    }
  },
  "environment": {
    "_": {
      "postman_variable_scope": "environment",
      "postman_exported_at": "2024-11-29T06:02:25.897Z",
      "postman_exported_using": "Postman/11.21.0"
    },
    "id": "4b4e8590-3ad2-477c-ab64-2b6b923d38ef",
    "name": "SharnTest",
    "values": [
      {
        "type": "any",
        "value": "Bearer 8cc2fb2d65333fab4f7a3aa752662dac66d862fb2afa9a5578155b94a3e9d32f",
        "key": "tokenId"
      },
      {
        "type": "any",
        "value": "",
        "key": "userid"
      },
      {
        "type": "any",
        "value": "Bearer 8cc2fb2d65333fab4f7a3aa752662dac66d862fb2afa9a5578155b94a3e9d32f",
        "key": "WorkFlowTokenID"
      },
      {
        "type": "any",
        "value": "https://gorest.co.in",
        "key": "WorkFlowBaseURL"
      }
    ]
  },
  "globals": {
    "id": "ad6302c7-6b8a-4ad9-85d9-62e8e8139a46",
    "values": []
  },
  "run": {
    "stats": {
      "iterations": {
        "total": 1,
        "pending": 0,
        "failed": 0
      },
      "items": {
        "total": 5,
        "pending": 0,
        "failed": 0
      },
      "scripts": {
        "total": 15,
        "pending": 0,
        "failed": 0
      },
      "prerequests": {
        "total": 5,
        "pending": 0,
        "failed": 0
      },
      "requests": {
        "total": 5,
        "pending": 0,
        "failed": 0
      },
      "tests": {
        "total": 5,
        "pending": 0,
        "failed": 0
      },
      "assertions": {
        "total": 10,
        "pending": 0,
        "failed": 0
      },
      "testScripts": {
        "total": 10,
        "pending": 0,
        "failed": 0
      },
      "prerequestScripts": {
        "total": 5,
        "pending": 0,
        "failed": 0
      }
    },
    "timings": {
      "responseAverage": 548.6,
      "responseMin": 345,
      "responseMax": 1210,
      "responseSd": 333.31582620691745,
      "dnsAverage": 0,
      "dnsMin": 0,
      "dnsMax": 0,
      "dnsSd": 0,
      "firstByteAverage": 0,
      "firstByteMin": 0,
      "firstByteMax": 0,
      "firstByteSd": 0,
      "started": 1732862964812,
      "completed": 1732862968200
    },
    "executions": [
      {
        "cursor": {
          "position": 0,
          "iteration": 0,
          "length": 5,
          "cycles": 1,
          "empty": false,
          "eof": false,
          "bof": true,
          "cr": false,
          "ref": "10f9b8de-3727-4b47-be8e-12a4b04f7ebd",
          "httpRequestId": "dcfacaed-ab8e-46a3-95be-2aae4ab2c903"
        },
        "item": {
          "id": "699a3900-3faf-421c-b4d4-af805d6ff6e6",
          "name": "1.POST_CreateUser",
          "request": {
            "url": {
              "path": [
                "public",
                "v2",
                "users"
              ],
              "host": [
                "{{WorkFlowBaseURL}}"
              ],
              "query": [],
              "variable": []
            },
            "header": [
              {
                "key": "Authorization",
                "value": "{{WorkFlowTokenID}}"
              }
            ],
            "method": "POST",
            "body": {
              "mode": "raw",
              "raw": "{\r\n    \"name\": \"{{$randomFirstName}}\",//this is name \r\n    \"email\": \"sha_{{$randomEmail}}\",// this is email id\r\n    \"gender\": \"male\", // this gender identity\r\n    \"status\": \"inactive\" // user status\r\n}",
              "options": {
                "raw": {
                  "language": "json"
                }
              }
            }
          },
          "response": [],
          "event": [
            {
              "listen": "test",
              "script": {
                "id": "c709845b-1a12-449f-be8c-6ef20427a30d",
                "type": "text/javascript",
                "packages": {},
                "exec": [
                  "const res = pm.response.json();\r",
                  "const userId = res.id;\r",
                  "const userName = res.name;\r",
                  "const userEmail = res.email;\r",
                  "const userGender = res.gender;\r",
                  "const userStatus = res.status;\r",
                  "\r",
                  "console.log(\"User Id is :\"+userId);\r",
                  "console.log(\"User NAme is :\"+userName);\r",
                  "console.log(\"User MailID is :\"+userEmail);\r",
                  "console.log(\"User Gender is :\"+userGender);\r",
                  "console.log(\"User Gender is :\"+userStatus);\r",
                  "\r",
                  "//use local variable to set the userid\r",
                  "pm.variables.set(\"user_id\",userId);\r",
                  "\r",
                  "pm.test(\"Status code is 201\", function () {\r",
                  "    pm.response.to.have.status(201);\r",
                  "});\r",
                  "\r",
                  "\r",
                  ""
                ],
                "_lastExecutionId": "138e2c59-44a4-4551-9d81-fb623489efad"
              }
            }
          ]
        },
        "request": {
          "url": {
            "protocol": "https",
            "path": [
              "public",
              "v2",
              "users"
            ],
            "host": [
              "gorest",
              "co",
              "in"
            ],
            "query": [],
            "variable": []
          },
          "header": [
            {
              "key": "Authorization",
              "value": "Bearer 8cc2fb2d65333fab4f7a3aa752662dac66d862fb2afa9a5578155b94a3e9d32f"
            },
            {
              "key": "Content-Type",
              "value": "application/json",
              "system": true
            },
            {
              "key": "User-Agent",
              "value": "PostmanRuntime/7.39.1",
              "system": true
            },
            {
              "key": "Accept",
              "value": "*/*",
              "system": true
            },
            {
              "key": "Cache-Control",
              "value": "no-cache",
              "system": true
            },
            {
              "key": "Postman-Token",
              "value": "44d0bb1d-e0d6-4744-8d19-a680a36a2362",
              "system": true
            },
            {
              "key": "Host",
              "value": "gorest.co.in",
              "system": true
            },
            {
              "key": "Accept-Encoding",
              "value": "gzip, deflate, br",
              "system": true
            },
            {
              "key": "Connection",
              "value": "keep-alive",
              "system": true
            },
            {
              "key": "Content-Length",
              "value": "112",
              "system": true
            }
          ],
          "method": "POST",
          "body": {
            "mode": "raw",
            "raw": "{\r\n    \"name\": \"Coby\",\n    \"email\": \"sha_Asha71@hotmail.com\",\n    \"gender\": \"male\", \n    \"status\": \"inactive\" \n}",
            "options": {
              "raw": {
                "language": "json"
              }
            }
          }
        },
        "response": {
          "id": "9ea94c23-aabe-44f3-b834-113752002f32",
          "status": "Created",
          "code": 201,
          "header": [
            {
              "key": "Date",
              "value": "Fri, 29 Nov 2024 06:49:26 GMT"
            },
            {
              "key": "Content-Type",
              "value": "application/json; charset=utf-8"
            },
            {
              "key": "Content-Length",
              "value": "97"
            },
            {
              "key": "Connection",
              "value": "keep-alive"
            },
            {
              "key": "Cache-Control",
              "value": "max-age=0, private, must-revalidate"
            },
            {
              "key": "etag",
              "value": "W/\"132b9b0cdd753bc227e2bcf62416704e\""
            },
            {
              "key": "location",
              "value": "https://gorest.co.in/public/v2/users/7551580"
            },
            {
              "key": "referrer-policy",
              "value": "strict-origin-when-cross-origin"
            },
            {
              "key": "vary",
              "value": "Origin"
            },
            {
              "key": "x-content-type-options",
              "value": "nosniff"
            },
            {
              "key": "x-download-options",
              "value": "noopen"
            },
            {
              "key": "x-frame-options",
              "value": "SAMEORIGIN"
            },
            {
              "key": "x-permitted-cross-domain-policies",
              "value": "none"
            },
            {
              "key": "x-ratelimit-limit",
              "value": "90"
            },
            {
              "key": "x-ratelimit-remaining",
              "value": "85"
            },
            {
              "key": "x-ratelimit-reset",
              "value": "1"
            },
            {
              "key": "x-request-id",
              "value": "0f571aa0-adba-41b2-b04a-17753a1f19fb"
            },
            {
              "key": "x-runtime",
              "value": "0.091640"
            },
            {
              "key": "x-xss-protection",
              "value": "0"
            },
            {
              "key": "CF-Cache-Status",
              "value": "DYNAMIC"
            },
            {
              "key": "Report-To",
              "value": "{\"endpoints\":[{\"url\":\"https:\\/\\/a.nel.cloudflare.com\\/report\\/v4?s=AdvpzBBqg20nE6afBhStpspW0J2suQuPROYfR8XOlCd9byocv1C%2B4YPq1LT0%2BJFL3SHgAs%2FmRgG73WcXSHFSVMNRO19opxaMQXuYefhCJiAZ2Z0yrvOdcUMDJ0iPzrI%3D\"}],\"group\":\"cf-nel\",\"max_age\":604800}"
            },
            {
              "key": "NEL",
              "value": "{\"success_fraction\":0,\"report_to\":\"cf-nel\",\"max_age\":604800}"
            },
            {
              "key": "Server",
              "value": "cloudflare"
            },
            {
              "key": "CF-RAY",
              "value": "8ea0a85f8e740d7a-MRS"
            },
            {
              "key": "alt-svc",
              "value": "h3=\":443\"; ma=86400"
            },
            {
              "key": "server-timing",
              "value": "cfL4;desc=\"?proto=TCP&rtt=191823&min_rtt=120958&rtt_var=95977&sent=5&recv=5&lost=0&retrans=0&sent_bytes=2598&recv_bytes=965&delivery_rate=31002&cwnd=247&unsent_bytes=0&cid=c7d623cd0c6ac3c8&ts=714&x=0\""
            }
          ],
          "stream": {
            "type": "Buffer",
            "data": [
              123,
              34,
              105,
              100,
              34,
              58,
              55,
              53,
              53,
              49,
              53,
              56,
              48,
              44,
              34,
              110,
              97,
              109,
              101,
              34,
              58,
              34,
              67,
              111,
              98,
              121,
              34,
              44,
              34,
              101,
              109,
              97,
              105,
              108,
              34,
              58,
              34,
              115,
              104,
              97,
              95,
              65,
              115,
              104,
              97,
              55,
              49,
              64,
              104,
              111,
              116,
              109,
              97,
              105,
              108,
              46,
              99,
              111,
              109,
              34,
              44,
              34,
              103,
              101,
              110,
              100,
              101,
              114,
              34,
              58,
              34,
              109,
              97,
              108,
              101,
              34,
              44,
              34,
              115,
              116,
              97,
              116,
              117,
              115,
              34,
              58,
              34,
              105,
              110,
              97,
              99,
              116,
              105,
              118,
              101,
              34,
              125
            ]
          },
          "cookie": [],
          "responseTime": 1210,
          "responseSize": 97
        },
        "id": "699a3900-3faf-421c-b4d4-af805d6ff6e6",
        "assertions": [
          {
            "assertion": "Response time is less than 5000ms",
            "skipped": false
          },
          {
            "assertion": "Status code is 201",
            "skipped": false
          }
        ]
      },
      {
        "cursor": {
          "ref": "44ab8178-c855-4ec0-961a-71ff9fe89faf",
          "length": 5,
          "cycles": 1,
          "position": 1,
          "iteration": 0,
          "httpRequestId": "618f7697-8d99-44c9-b12f-697d90102414"
        },
        "item": {
          "id": "b2e41b24-5776-4ce3-94ad-11185a76c607",
          "name": "2.GET_CreatedUser",
          "request": {
            "url": {
              "path": [
                "public",
                "v2",
                "users",
                "{{user_id}}"
              ],
              "host": [
                "{{WorkFlowBaseURL}}"
              ],
              "query": [],
              "variable": []
            },
            "header": [
              {
                "key": "Authorization",
                "value": "Bearer 8cc2fb2d65333fab4f7a3aa752662dac66d862fb2afa9a5578155b94a3e9d32f"
              }
            ],
            "method": "GET",
            "body": {
              "mode": "raw",
              "raw": "{\r\n    \"name\": \"{{$randomFirstName}}\",\r\n    \"email\": \"sha_{{$randomEmail}}\",\r\n    \"gender\": \"male\",\r\n    \"status\": \"inactive\"\r\n}",
              "options": {
                "raw": {
                  "language": "json"
                }
              }
            }
          },
          "response": [],
          "event": [
            {
              "listen": "test",
              "script": {
                "id": "aaa8f7e5-1603-4765-b9fa-d5bac7281d37",
                "type": "text/javascript",
                "packages": {},
                "exec": [
                  "pm.test(\"Status code is 200\", function () {\r",
                  "    pm.response.to.have.status(200);\r",
                  "});\r",
                  ""
                ],
                "_lastExecutionId": "13cc12bd-2d7d-4df2-860c-16aae55c61c1"
              }
            }
          ],
          "protocolProfileBehavior": {
            "disableBodyPruning": true
          }
        },
        "request": {
          "url": {
            "protocol": "https",
            "path": [
              "public",
              "v2",
              "users",
              "7551580"
            ],
            "host": [
              "gorest",
              "co",
              "in"
            ],
            "query": [],
            "variable": []
          },
          "header": [
            {
              "key": "Authorization",
              "value": "Bearer 8cc2fb2d65333fab4f7a3aa752662dac66d862fb2afa9a5578155b94a3e9d32f"
            },
            {
              "key": "Content-Type",
              "value": "application/json",
              "system": true
            },
            {
              "key": "User-Agent",
              "value": "PostmanRuntime/7.39.1",
              "system": true
            },
            {
              "key": "Accept",
              "value": "*/*",
              "system": true
            },
            {
              "key": "Cache-Control",
              "value": "no-cache",
              "system": true
            },
            {
              "key": "Postman-Token",
              "value": "87a82a04-0e50-4fbf-871a-b64910b117d8",
              "system": true
            },
            {
              "key": "Host",
              "value": "gorest.co.in",
              "system": true
            },
            {
              "key": "Accept-Encoding",
              "value": "gzip, deflate, br",
              "system": true
            },
            {
              "key": "Connection",
              "value": "keep-alive",
              "system": true
            },
            {
              "key": "Content-Length",
              "value": "125",
              "system": true
            }
          ],
          "method": "GET",
          "body": {
            "mode": "raw",
            "raw": "{\r\n    \"name\": \"Shaylee\",\r\n    \"email\": \"sha_Peyton.Weimann72@gmail.com\",\r\n    \"gender\": \"male\",\r\n    \"status\": \"inactive\"\r\n}",
            "options": {
              "raw": {
                "language": "json"
              }
            }
          }
        },
        "response": {
          "id": "13ac8a1d-cd6e-4dfb-af2f-376fb4866592",
          "status": "OK",
          "code": 200,
          "header": [
            {
              "key": "Date",
              "value": "Fri, 29 Nov 2024 06:49:26 GMT"
            },
            {
              "key": "Content-Type",
              "value": "application/json; charset=utf-8"
            },
            {
              "key": "Transfer-Encoding",
              "value": "chunked"
            },
            {
              "key": "Connection",
              "value": "keep-alive"
            },
            {
              "key": "Cache-Control",
              "value": "max-age=0, private, must-revalidate"
            },
            {
              "key": "etag",
              "value": "W/\"132b9b0cdd753bc227e2bcf62416704e\""
            },
            {
              "key": "referrer-policy",
              "value": "strict-origin-when-cross-origin"
            },
            {
              "key": "vary",
              "value": "Origin"
            },
            {
              "key": "x-content-type-options",
              "value": "nosniff"
            },
            {
              "key": "x-download-options",
              "value": "noopen"
            },
            {
              "key": "x-frame-options",
              "value": "SAMEORIGIN"
            },
            {
              "key": "x-permitted-cross-domain-policies",
              "value": "none"
            },
            {
              "key": "x-ratelimit-limit",
              "value": "90"
            },
            {
              "key": "x-ratelimit-remaining",
              "value": "89"
            },
            {
              "key": "x-ratelimit-reset",
              "value": "2"
            },
            {
              "key": "x-request-id",
              "value": "4f835497-2ba1-46ef-b116-af119f9de5bc"
            },
            {
              "key": "x-runtime",
              "value": "0.061577"
            },
            {
              "key": "x-xss-protection",
              "value": "0"
            },
            {
              "key": "CF-Cache-Status",
              "value": "DYNAMIC"
            },
            {
              "key": "Report-To",
              "value": "{\"endpoints\":[{\"url\":\"https:\\/\\/a.nel.cloudflare.com\\/report\\/v4?s=K%2BoHPwYWKHeQUWHo9%2B%2B5W10PLljlN%2B9ion2NJqSRqAfMLrpBmIaWQIHIjsSsrwFdngj97xQfNCsxL%2F4wYs7JbtCZQF6l4NDwxd%2B1CfJo6ea%2FYy7plDG8DBGnMSTCkR8%3D\"}],\"group\":\"cf-nel\",\"max_age\":604800}"
            },
            {
              "key": "NEL",
              "value": "{\"success_fraction\":0,\"report_to\":\"cf-nel\",\"max_age\":604800}"
            },
            {
              "key": "Server",
              "value": "cloudflare"
            },
            {
              "key": "CF-RAY",
              "value": "8ea0a8653ce40d7a-MRS"
            },
            {
              "key": "Content-Encoding",
              "value": "br"
            },
            {
              "key": "alt-svc",
              "value": "h3=\":443\"; ma=86400"
            },
            {
              "key": "server-timing",
              "value": "cfL4;desc=\"?proto=TCP&rtt=181738&min_rtt=119732&rtt_var=69651&sent=9&recv=8&lost=0&retrans=0&sent_bytes=4498&recv_bytes=1500&delivery_rate=31002&cwnd=250&unsent_bytes=0&cid=c7d623cd0c6ac3c8&ts=1265&x=0\""
            }
          ],
          "stream": {
            "type": "Buffer",
            "data": [
              123,
              34,
              105,
              100,
              34,
              58,
              55,
              53,
              53,
              49,
              53,
              56,
              48,
              44,
              34,
              110,
              97,
              109,
              101,
              34,
              58,
              34,
              67,
              111,
              98,
              121,
              34,
              44,
              34,
              101,
              109,
              97,
              105,
              108,
              34,
              58,
              34,
              115,
              104,
              97,
              95,
              65,
              115,
              104,
              97,
              55,
              49,
              64,
              104,
              111,
              116,
              109,
              97,
              105,
              108,
              46,
              99,
              111,
              109,
              34,
              44,
              34,
              103,
              101,
              110,
              100,
              101,
              114,
              34,
              58,
              34,
              109,
              97,
              108,
              101,
              34,
              44,
              34,
              115,
              116,
              97,
              116,
              117,
              115,
              34,
              58,
              34,
              105,
              110,
              97,
              99,
              116,
              105,
              118,
              101,
              34,
              125
            ]
          },
          "cookie": [],
          "responseTime": 363,
          "responseSize": 97
        },
        "id": "b2e41b24-5776-4ce3-94ad-11185a76c607",
        "assertions": [
          {
            "assertion": "Response time is less than 5000ms",
            "skipped": false
          },
          {
            "assertion": "Status code is 200",
            "skipped": false
          }
        ]
      },
      {
        "cursor": {
          "ref": "834c0c13-f242-40cc-a159-2fe1437a5877",
          "length": 5,
          "cycles": 1,
          "position": 2,
          "iteration": 0,
          "httpRequestId": "7d67cf09-45f5-429c-aa6e-7acf44fe3909"
        },
        "item": {
          "id": "96381c77-108a-4dc3-ae6b-3bd85708c723",
          "name": "3.PATCH_UpdateUSer",
          "request": {
            "url": {
              "path": [
                "public",
                "v2",
                "users",
                "",
                "{{user_id}}"
              ],
              "host": [
                "{{WorkFlowBaseURL}}"
              ],
              "query": [],
              "variable": []
            },
            "header": [
              {
                "key": "Authorization",
                "value": "{{WorkFlowTokenID}}"
              }
            ],
            "method": "PATCH",
            "body": {
              "mode": "raw",
              "raw": "{\r\n    \"name\": \"{{$randomFirstName}}\",//this is name \r\n    \"email\": \"sha_{{$randomEmail}}\"// this is email id\r\n  \r\n}",
              "options": {
                "raw": {
                  "language": "json"
                }
              }
            }
          },
          "response": [],
          "event": [
            {
              "listen": "test",
              "script": {
                "id": "d0d73b52-3a5e-451d-b7ee-07463a452ddf",
                "type": "text/javascript",
                "packages": {},
                "exec": [
                  "pm.test(\"Status code is 200\", function () {\r",
                  "    pm.response.to.have.status(200);\r",
                  "});\r",
                  ""
                ],
                "_lastExecutionId": "d8fddab8-0446-4a44-ba77-5c35e8d9c807"
              }
            }
          ]
        },
        "request": {
          "url": {
            "protocol": "https",
            "path": [
              "public",
              "v2",
              "users",
              "",
              "7551580"
            ],
            "host": [
              "gorest",
              "co",
              "in"
            ],
            "query": [],
            "variable": []
          },
          "header": [
            {
              "key": "Authorization",
              "value": "Bearer 8cc2fb2d65333fab4f7a3aa752662dac66d862fb2afa9a5578155b94a3e9d32f"
            },
            {
              "key": "Content-Type",
              "value": "application/json",
              "system": true
            },
            {
              "key": "User-Agent",
              "value": "PostmanRuntime/7.39.1",
              "system": true
            },
            {
              "key": "Accept",
              "value": "*/*",
              "system": true
            },
            {
              "key": "Cache-Control",
              "value": "no-cache",
              "system": true
            },
            {
              "key": "Postman-Token",
              "value": "486bba05-8235-4693-8b5c-a672e976cdf8",
              "system": true
            },
            {
              "key": "Host",
              "value": "gorest.co.in",
              "system": true
            },
            {
              "key": "Accept-Encoding",
              "value": "gzip, deflate, br",
              "system": true
            },
            {
              "key": "Connection",
              "value": "keep-alive",
              "system": true
            },
            {
              "key": "Content-Length",
              "value": "76",
              "system": true
            }
          ],
          "method": "PATCH",
          "body": {
            "mode": "raw",
            "raw": "{\r\n    \"name\": \"Porter\",\n    \"email\": \"sha_Michael.Torphy@hotmail.com\"\n  \r\n}",
            "options": {
              "raw": {
                "language": "json"
              }
            }
          }
        },
        "response": {
          "id": "f6f2f4d0-8734-4199-96e6-52591ab36d81",
          "status": "OK",
          "code": 200,
          "header": [
            {
              "key": "Date",
              "value": "Fri, 29 Nov 2024 06:49:27 GMT"
            },
            {
              "key": "Content-Type",
              "value": "application/json; charset=utf-8"
            },
            {
              "key": "Transfer-Encoding",
              "value": "chunked"
            },
            {
              "key": "Connection",
              "value": "keep-alive"
            },
            {
              "key": "Cache-Control",
              "value": "max-age=0, private, must-revalidate"
            },
            {
              "key": "etag",
              "value": "W/\"832ee733d5e524ea9cc4d35badfed457\""
            },
            {
              "key": "referrer-policy",
              "value": "strict-origin-when-cross-origin"
            },
            {
              "key": "vary",
              "value": "Origin"
            },
            {
              "key": "x-content-type-options",
              "value": "nosniff"
            },
            {
              "key": "x-download-options",
              "value": "noopen"
            },
            {
              "key": "x-frame-options",
              "value": "SAMEORIGIN"
            },
            {
              "key": "x-permitted-cross-domain-policies",
              "value": "none"
            },
            {
              "key": "x-ratelimit-limit",
              "value": "90"
            },
            {
              "key": "x-ratelimit-remaining",
              "value": "88"
            },
            {
              "key": "x-ratelimit-reset",
              "value": "2"
            },
            {
              "key": "x-request-id",
              "value": "66d834b8-4551-4a89-a80c-e127de24c7ca"
            },
            {
              "key": "x-runtime",
              "value": "0.121045"
            },
            {
              "key": "x-xss-protection",
              "value": "0"
            },
            {
              "key": "CF-Cache-Status",
              "value": "DYNAMIC"
            },
            {
              "key": "Report-To",
              "value": "{\"endpoints\":[{\"url\":\"https:\\/\\/a.nel.cloudflare.com\\/report\\/v4?s=EHwq1uCrGoLPkvCX%2FMsNN8zA%2F0RNdXEAIEDadkZqko1ONzrrJautbrC1RuB8qGzW8hwu5DaqOjk3cNqdyqnnuntZ1rYMp%2B89vdIuZ5EF6y8Mr89Aj2vpogB7PU5bsik%3D\"}],\"group\":\"cf-nel\",\"max_age\":604800}"
            },
            {
              "key": "NEL",
              "value": "{\"success_fraction\":0,\"report_to\":\"cf-nel\",\"max_age\":604800}"
            },
            {
              "key": "Server",
              "value": "cloudflare"
            },
            {
              "key": "CF-RAY",
              "value": "8ea0a86878db0d7a-MRS"
            },
            {
              "key": "Content-Encoding",
              "value": "br"
            },
            {
              "key": "alt-svc",
              "value": "h3=\":443\"; ma=86400"
            },
            {
              "key": "server-timing",
              "value": "cfL4;desc=\"?proto=TCP&rtt=167471&min_rtt=119732&rtt_var=63909&sent=14&recv=11&lost=0&retrans=0&sent_bytes=5949&recv_bytes=1988&delivery_rate=41360&cwnd=252&unsent_bytes=0&cid=c7d623cd0c6ac3c8&ts=1869&x=0\""
            }
          ],
          "stream": {
            "type": "Buffer",
            "data": [
              123,
              34,
              101,
              109,
              97,
              105,
              108,
              34,
              58,
              34,
              115,
              104,
              97,
              95,
              77,
              105,
              99,
              104,
              97,
              101,
              108,
              46,
              84,
              111,
              114,
              112,
              104,
              121,
              64,
              104,
              111,
              116,
              109,
              97,
              105,
              108,
              46,
              99,
              111,
              109,
              34,
              44,
              34,
              110,
              97,
              109,
              101,
              34,
              58,
              34,
              80,
              111,
              114,
              116,
              101,
              114,
              34,
              44,
              34,
              105,
              100,
              34,
              58,
              55,
              53,
              53,
              49,
              53,
              56,
              48,
              44,
              34,
              103,
              101,
              110,
              100,
              101,
              114,
              34,
              58,
              34,
              109,
              97,
              108,
              101,
              34,
              44,
              34,
              115,
              116,
              97,
              116,
              117,
              115,
              34,
              58,
              34,
              105,
              110,
              97,
              99,
              116,
              105,
              118,
              101,
              34,
              125
            ]
          },
          "cookie": [],
          "responseTime": 463,
          "responseSize": 107
        },
        "id": "96381c77-108a-4dc3-ae6b-3bd85708c723",
        "assertions": [
          {
            "assertion": "Response time is less than 5000ms",
            "skipped": false
          },
          {
            "assertion": "Status code is 200",
            "skipped": false
          }
        ]
      },
      {
        "cursor": {
          "ref": "d70653e3-efaa-4d13-a83d-8b365d07b826",
          "length": 5,
          "cycles": 1,
          "position": 3,
          "iteration": 0,
          "httpRequestId": "b9c8fb7d-e0fc-48d9-9442-061fd78db5f1"
        },
        "item": {
          "id": "2a0c0a6d-a6a8-4943-8c7f-fda0a2fd2332",
          "name": "4.DELETE-User",
          "request": {
            "url": {
              "path": [
                "public",
                "v2",
                "users",
                "{{user_id}}"
              ],
              "host": [
                "{{WorkFlowBaseURL}}"
              ],
              "query": [],
              "variable": []
            },
            "header": [
              {
                "key": "Authorization",
                "value": "Bearer 8cc2fb2d65333fab4f7a3aa752662dac66d862fb2afa9a5578155b94a3e9d32f"
              }
            ],
            "method": "DELETE",
            "body": {
              "mode": "raw",
              "raw": "",
              "options": {
                "raw": {
                  "language": "json"
                }
              }
            }
          },
          "response": [],
          "event": [
            {
              "listen": "test",
              "script": {
                "id": "60c239ca-97ac-4953-849a-562af59ec5fc",
                "type": "text/javascript",
                "packages": {},
                "exec": [
                  "pm.test(\"Status code is 204\", function () {\r",
                  "    pm.response.to.have.status(204);\r",
                  "});\r",
                  ""
                ],
                "_lastExecutionId": "e4d78ded-e4b0-4e22-bd6e-b1c4c9498a2d"
              }
            }
          ]
        },
        "request": {
          "url": {
            "protocol": "https",
            "path": [
              "public",
              "v2",
              "users",
              "7551580"
            ],
            "host": [
              "gorest",
              "co",
              "in"
            ],
            "query": [],
            "variable": []
          },
          "header": [
            {
              "key": "Authorization",
              "value": "Bearer 8cc2fb2d65333fab4f7a3aa752662dac66d862fb2afa9a5578155b94a3e9d32f"
            },
            {
              "key": "User-Agent",
              "value": "PostmanRuntime/7.39.1",
              "system": true
            },
            {
              "key": "Accept",
              "value": "*/*",
              "system": true
            },
            {
              "key": "Cache-Control",
              "value": "no-cache",
              "system": true
            },
            {
              "key": "Postman-Token",
              "value": "6933db50-cdd9-4579-a7cc-365f5e62da4e",
              "system": true
            },
            {
              "key": "Host",
              "value": "gorest.co.in",
              "system": true
            },
            {
              "key": "Accept-Encoding",
              "value": "gzip, deflate, br",
              "system": true
            },
            {
              "key": "Connection",
              "value": "keep-alive",
              "system": true
            }
          ],
          "method": "DELETE",
          "body": {
            "mode": "raw",
            "raw": "",
            "options": {
              "raw": {
                "language": "json"
              }
            }
          }
        },
        "response": {
          "id": "36cfddfb-9ea0-4f31-9457-d4848f8ada25",
          "status": "No Content",
          "code": 204,
          "header": [
            {
              "key": "Date",
              "value": "Fri, 29 Nov 2024 06:49:27 GMT"
            },
            {
              "key": "Connection",
              "value": "keep-alive"
            },
            {
              "key": "Cache-Control",
              "value": "no-cache"
            },
            {
              "key": "referrer-policy",
              "value": "strict-origin-when-cross-origin"
            },
            {
              "key": "vary",
              "value": "Origin"
            },
            {
              "key": "x-content-type-options",
              "value": "nosniff"
            },
            {
              "key": "x-download-options",
              "value": "noopen"
            },
            {
              "key": "x-frame-options",
              "value": "SAMEORIGIN"
            },
            {
              "key": "x-permitted-cross-domain-policies",
              "value": "none"
            },
            {
              "key": "x-ratelimit-limit",
              "value": "90"
            },
            {
              "key": "x-ratelimit-remaining",
              "value": "87"
            },
            {
              "key": "x-ratelimit-reset",
              "value": "3"
            },
            {
              "key": "x-request-id",
              "value": "2791580f-778a-45d5-b9cb-ecc054d0aa9c"
            },
            {
              "key": "x-runtime",
              "value": "0.072958"
            },
            {
              "key": "x-xss-protection",
              "value": "0"
            },
            {
              "key": "CF-Cache-Status",
              "value": "DYNAMIC"
            },
            {
              "key": "Report-To",
              "value": "{\"endpoints\":[{\"url\":\"https:\\/\\/a.nel.cloudflare.com\\/report\\/v4?s=SVfpDdPOzR0mMhQy7JxidHK4rUyijrYJyBbtpjSeI7okhp%2FRVHJ9bulE877lpl%2BHoq2efv80Liva3AVwi9xWr3jQEFxwcewezLMwumzVQOzSdsNFzMtBX0DmsgF0V4w%3D\"}],\"group\":\"cf-nel\",\"max_age\":604800}"
            },
            {
              "key": "NEL",
              "value": "{\"success_fraction\":0,\"report_to\":\"cf-nel\",\"max_age\":604800}"
            },
            {
              "key": "Server",
              "value": "cloudflare"
            },
            {
              "key": "CF-RAY",
              "value": "8ea0a86bec9e0d7a-MRS"
            },
            {
              "key": "alt-svc",
              "value": "h3=\":443\"; ma=86400"
            },
            {
              "key": "server-timing",
              "value": "cfL4;desc=\"?proto=TCP&rtt=156440&min_rtt=119732&rtt_var=55074&sent=19&recv=14&lost=0&retrans=0&sent_bytes=7401&recv_bytes=2348&delivery_rate=41495&cwnd=252&unsent_bytes=0&cid=c7d623cd0c6ac3c8&ts=2345&x=0\""
            }
          ],
          "stream": {
            "type": "Buffer",
            "data": []
          },
          "cookie": [],
          "responseTime": 362,
          "responseSize": 0
        },
        "id": "2a0c0a6d-a6a8-4943-8c7f-fda0a2fd2332",
        "assertions": [
          {
            "assertion": "Response time is less than 5000ms",
            "skipped": false
          },
          {
            "assertion": "Status code is 204",
            "skipped": false
          }
        ]
      },
      {
        "cursor": {
          "ref": "6d435883-efd9-45b3-ac96-d59487bcd3eb",
          "length": 5,
          "cycles": 1,
          "position": 4,
          "iteration": 0,
          "httpRequestId": "3684acb1-68bd-4339-b135-7cb74daef00b"
        },
        "item": {
          "id": "0aef6883-42a9-4bf2-b49f-54f661b2d1fd",
          "name": "5.GET_DEletedUser",
          "request": {
            "url": {
              "path": [
                "public",
                "v2",
                "users",
                "{{user_id}}"
              ],
              "host": [
                "{{WorkFlowBaseURL}}"
              ],
              "query": [],
              "variable": []
            },
            "header": [
              {
                "key": "Authorization",
                "value": "Bearer 8cc2fb2d65333fab4f7a3aa752662dac66d862fb2afa9a5578155b94a3e9d32f"
              }
            ],
            "method": "GET",
            "body": {
              "mode": "raw",
              "raw": "{\r\n    \"name\": \"{{$randomFirstName}}\",\r\n    \"email\": \"sha_{{$randomEmail}}\",\r\n    \"gender\": \"male\",\r\n    \"status\": \"inactive\"\r\n}",
              "options": {
                "raw": {
                  "language": "json"
                }
              }
            }
          },
          "response": [],
          "event": [
            {
              "listen": "test",
              "script": {
                "id": "b1277eaf-d3c7-497f-860e-93abf27911c2",
                "type": "text/javascript",
                "packages": {},
                "exec": [
                  "pm.test(\"Status code is 404\", function () {\r",
                  "    pm.response.to.have.status(404);\r",
                  "});\r",
                  ""
                ],
                "_lastExecutionId": "6e6b8c2e-0e6c-4432-8afc-12b4dbcb10ee"
              }
            }
          ],
          "protocolProfileBehavior": {
            "disableBodyPruning": true
          }
        },
        "request": {
          "url": {
            "protocol": "https",
            "path": [
              "public",
              "v2",
              "users",
              "7551580"
            ],
            "host": [
              "gorest",
              "co",
              "in"
            ],
            "query": [],
            "variable": []
          },
          "header": [
            {
              "key": "Authorization",
              "value": "Bearer 8cc2fb2d65333fab4f7a3aa752662dac66d862fb2afa9a5578155b94a3e9d32f"
            },
            {
              "key": "Content-Type",
              "value": "application/json",
              "system": true
            },
            {
              "key": "User-Agent",
              "value": "PostmanRuntime/7.39.1",
              "system": true
            },
            {
              "key": "Accept",
              "value": "*/*",
              "system": true
            },
            {
              "key": "Cache-Control",
              "value": "no-cache",
              "system": true
            },
            {
              "key": "Postman-Token",
              "value": "df4617db-deae-4ec6-9496-c9a95c02e9ad",
              "system": true
            },
            {
              "key": "Host",
              "value": "gorest.co.in",
              "system": true
            },
            {
              "key": "Accept-Encoding",
              "value": "gzip, deflate, br",
              "system": true
            },
            {
              "key": "Connection",
              "value": "keep-alive",
              "system": true
            },
            {
              "key": "Content-Length",
              "value": "117",
              "system": true
            }
          ],
          "method": "GET",
          "body": {
            "mode": "raw",
            "raw": "{\r\n    \"name\": \"Jackie\",\r\n    \"email\": \"sha_Dusty92@hotmail.com\",\r\n    \"gender\": \"male\",\r\n    \"status\": \"inactive\"\r\n}",
            "options": {
              "raw": {
                "language": "json"
              }
            }
          }
        },
        "response": {
          "id": "c2e86f41-f963-4fd1-a9e3-5bfc99495d66",
          "status": "Not Found",
          "code": 404,
          "header": [
            {
              "key": "Date",
              "value": "Fri, 29 Nov 2024 06:49:28 GMT"
            },
            {
              "key": "Content-Type",
              "value": "application/json; charset=utf-8"
            },
            {
              "key": "Content-Length",
              "value": "32"
            },
            {
              "key": "Connection",
              "value": "keep-alive"
            },
            {
              "key": "Cache-Control",
              "value": "no-cache"
            },
            {
              "key": "referrer-policy",
              "value": "strict-origin-when-cross-origin"
            },
            {
              "key": "vary",
              "value": "Origin"
            },
            {
              "key": "x-content-type-options",
              "value": "nosniff"
            },
            {
              "key": "x-download-options",
              "value": "noopen"
            },
            {
              "key": "x-frame-options",
              "value": "SAMEORIGIN"
            },
            {
              "key": "x-permitted-cross-domain-policies",
              "value": "none"
            },
            {
              "key": "x-ratelimit-limit",
              "value": "90"
            },
            {
              "key": "x-ratelimit-remaining",
              "value": "86"
            },
            {
              "key": "x-ratelimit-reset",
              "value": "4"
            },
            {
              "key": "x-request-id",
              "value": "e6fa2a0c-55bc-4097-a112-8aae44c5e08f"
            },
            {
              "key": "x-runtime",
              "value": "0.048718"
            },
            {
              "key": "x-xss-protection",
              "value": "0"
            },
            {
              "key": "CF-Cache-Status",
              "value": "DYNAMIC"
            },
            {
              "key": "Report-To",
              "value": "{\"endpoints\":[{\"url\":\"https:\\/\\/a.nel.cloudflare.com\\/report\\/v4?s=O0WOnLaMCYr0dViH8VP4ck5ieJr%2BXAZPnquGJsWMsAwpCjq1h8EQCcJktCUx1oX4pK1NX7lrMmDnI1sexkagswgG8AXhAyy2Y4XEHsrTbA%2Bz9LLgVzHrTYov6j6wK6U%3D\"}],\"group\":\"cf-nel\",\"max_age\":604800}"
            },
            {
              "key": "NEL",
              "value": "{\"success_fraction\":0,\"report_to\":\"cf-nel\",\"max_age\":604800}"
            },
            {
              "key": "Server",
              "value": "cloudflare"
            },
            {
              "key": "CF-RAY",
              "value": "8ea0a86ebfa90d7a-MRS"
            },
            {
              "key": "alt-svc",
              "value": "h3=\":443\"; ma=86400"
            },
            {
              "key": "server-timing",
              "value": "cfL4;desc=\"?proto=TCP&rtt=157267&min_rtt=119732&rtt_var=42960&sent=21&recv=16&lost=0&retrans=0&sent_bytes=8543&recv_bytes=2875&delivery_rate=41495&cwnd=252&unsent_bytes=0&cid=c7d623cd0c6ac3c8&ts=2769&x=0\""
            }
          ],
          "stream": {
            "type": "Buffer",
            "data": [
              123,
              34,
              109,
              101,
              115,
              115,
              97,
              103,
              101,
              34,
              58,
              34,
              82,
              101,
              115,
              111,
              117,
              114,
              99,
              101,
              32,
              110,
              111,
              116,
              32,
              102,
              111,
              117,
              110,
              100,
              34,
              125
            ]
          },
          "cookie": [],
          "responseTime": 345,
          "responseSize": 32
        },
        "id": "0aef6883-42a9-4bf2-b49f-54f661b2d1fd",
        "assertions": [
          {
            "assertion": "Response time is less than 5000ms",
            "skipped": false
          },
          {
            "assertion": "Status code is 404",
            "skipped": false
          }
        ]
      }
    ],
    "transfers": {
      "responseTotal": 333
    },
    "failures": [],
    "error": null
  }
}